handlebar_google_adk/__init__.py
handlebar_google_adk/api.py
handlebar_google_adk/plugin.py
handlebar_google_adk/runner.py
handlebar_google_adk-0.1.0.dist-info/WHEEL
handlebar_google_adk-0.1.0.dist-info/METADATA
handlebar_google_adk-0.1.0.dist-info/RECORD
