Metadata-Version: 2.4
Name: handlebar-google-adk
Version: 0.1.0
Summary: Handlebar AI governance for Google-ADK agents
Keywords: governance,ai,agent,llm,guardrails,handlebar,safety
Author: Handlebar Team
Author-email: Handlebar Team <contact@gethandlebar.com>
License-Expression: Apache-2.0
Requires-Dist: google-adk>=1.19.0
Requires-Dist: handlebar-core==0.1.0
Requires-Python: >=3.13
